{"properties":{"billing_address":{"type":"text","fields":{"keyword":{"type":"keyword","ignore_above":256}}},"billing_city":{"type":"text","fields":{"keyword":{"type":"keyword","ignore_above":256}}},"billing_country":{"type":"text","fields":{"keyword":{"type":"keyword","ignore_above":256}}},"billing_postal_code":{"type":"text","fields":{"keyword":{"type":"keyword","ignore_above":256}}},"billing_state":{"type":"text","fields":{"keyword":{"type":"keyword","ignore_above":256}}},"customer_id":{"type":"long"},"id":{"type":"long"},"invoice_date":{"type":"text","fields":{"keyword":{"type":"keyword","ignore_above":256}}},"total":{"type":"float"}}}